vps_brain_client/__init__.py
vps_brain_client/client.py
vps_brain_client/models.py
vps_brain_client/tests/test_client.py
vps_brain_client-0.1.0.dist-info/licenses/LICENSE
vps_brain_client-0.1.0.dist-info/METADATA
vps_brain_client-0.1.0.dist-info/WHEEL
vps_brain_client-0.1.0.dist-info/top_level.txt
vps_brain_client-0.1.0.dist-info/RECORD
